<?xml version="1.0" encoding="utf-8" ?>
<config>
    <acl>
        <resources>
            <admin>
                <children>
                    <system>
                        <children>
                            <config>
                                <children>
                                    <codecia_dynamicfilter translate="title" module="codecia_dynamicfilter">
                                        <title>Codecia Dynamic Filter</title>
                                    </codecia_dynamicfilter>
                                </children>
                            </config>
                        </children>
                    </system>
                </children>
            </admin>
        </resources>
    </acl>
</config>

